Workbook

Sheet Inicio
B2: Evaluación de proveedores de GPS y de rutas
B3: Para comparar con los mismos criterios, decidir quién pasa a un piloto y dejar la decisión documentada.
B5: Cómo usarla, paso a paso
B6: 1. Define criterios y pesos | C6: En Criterios, ajusta los pesos a lo que tu operación necesita (deben sumar 100) y marca los eliminatorios. Hazlo antes de hablar con ningún proveedor.
B7: 2. Elige 3 candidatos | C7: No más de tres, para poder compararlos a fondo. Escribe sus nombres en los encabezados de Evaluación (celdas azules).
B8: 3. Haz las mismas preguntas | C8: En Preguntas hay 19 preguntas. Anota la respuesta de cada proveedor y pide que muestren, no que cuenten.
B9: 4. Califica después de cada demostración | C9: En Evaluación, califica de 1 a 5 con la escala de cada criterio. No esperes a la semana siguiente: se olvida.
B10: 5. Calcula el costo | C10: En Costos, escribe los precios por escrito. Compara el total a 24 meses, no solo la mensualidad.
B11: 6. Prueba al mejor en un piloto | C11: En Piloto, mide las mismas cosas antes y durante unas 2 semanas con 3 a 5 vehículos de tipos distintos.
B12: 7. Decide y documenta | C12: Escribe la decisión y el motivo en Piloto. Así queda el argumento para tu jefe y para ti.
B14: Escala de calificación
B15: 1 | C15: No cumple.
B16: 2 | C16: Débil: cumple a medias o con mucho esfuerzo.
B17: 3 | C17: Cumple lo básico.
B18: 4 | C18: Bueno, con detalles menores.
B19: 5 | C19: Excelente: claramente mejor de lo que necesitas.
B21: Reglas para que la comparación sea justa
B22: Los mismos criterios para todos | C22: No cambies los pesos después de ver a los proveedores.
B23: Una sola persona califica | C23: O califiquen dos y promedien. Mezclar criterios distorsiona el resultado.
B24: Evidencia, no promesas | C24: Califica lo que viste funcionar o lo que consta por escrito.
B25: Eliminatorios | C25: Quien saque 2 o menos en un criterio eliminatorio queda descartado, aunque tenga buen puntaje total.
B26: El puntaje ayuda a decidir quién pasa al piloto | C26: La decisión final se toma con el piloto y el costo, no con el puntaje solo.
B28: Candidatos para investigar (no son recomendaciones)
B29: GPS y telemática | C29: Informac (producto Systrack, sobre la plataforma GpsGate; empresa dominicana), Geotab, Gurtam (Wialon, por distribuidores locales) y Samsara. La disponibilidad de Samsara en la República Dominicana no está confirmada.
B30: Rutas y despacho | C30: Routific (app del conductor en español desde febrero de 2026), OptimoRoute (app del conductor en español), Onfleet (para flotas propias de unos 3 a 50 vehículos).
B31: Aviso | C31: Esta lista sale de una investigación general. No he evaluado a estos proveedores ni verificado precios o disponibilidad en la República Dominicana: confírmalo con cada uno.
B33: Colores y límites
B34: Celda azul claro con texto azul | C34: Aquí escribes tú.
B35: Celda amarillo claro | C35: Ejemplo ficticio. No la tomes como un dato real.
B36: Celda gris | C36: Se calcula sola.
B37: Límites | C37: El puntaje mide lo que tú califiques. Si los criterios o los pesos no reflejan tu operación, el resultado tampoco lo hará. Revisa los pesos con tu jefe.

Sheet Criterios
A1: Criterios y pesos
A2: Define los pesos ANTES de ver a los proveedores. Deben sumar 100. Los criterios marcados Sí en Eliminatorio descartan al proveedor que saque 2 o menos.
A4: # | B4: Criterio | C4: Qué se mide y cómo calificar (1 a 5) | D4: Peso (%) | E4: Eliminatorio | F4: Aplica a
A5: 1 | B5: Seguimiento en vivo | C5: La posición se actualiza con la frecuencia suficiente y se ve claramente en el mapa. 1 = se actualiza cada varios minutos o falla; 5 = casi en tiempo real y estable. | D5: 9 | E5: No | F5: Ambos
A6: 2 | B6: Geocercas y alertas configurables | C6: Avisos de llegada, salida, desvío, parada larga y exceso de velocidad, a quién y por qué medio. 1 = sin alertas; 5 = alertas flexibles por WhatsApp o correo. | D6: 7 | E6: No | F6: GPS
A7: 3 | B7: Historial y reportes | C7: Recorridos pasados y reportes de velocidad, frenazos, ralentí y kilómetros. 1 = casi sin reportes; 5 = completos y programables. | D7: 7 | E7: No | F7: GPS
A8: 4 | B8: Cobertura y fiabilidad en nuestras zonas | C8: Funciona en Santo Domingo y en las rutas largas (Santiago, Punta Cana) sin cortes frecuentes. Pídelo probado, no prometido. | D8: 7 | E8: Sí | F8: GPS
A9: 5 | B9: Funciona con motos | C9: Rastreador pequeño o app en el teléfono del conductor, con batería y robustez razonables. | D9: 5 | E9: No | F9: Ambos
A10: 6 | B10: Planificación de rutas con ventanas de tiempo | C10: Ordena paradas, respeta horarios prometidos y permite varios tipos de vehículo. 1 = manual; 5 = automático y ajustable. | D10: 7 | E10: No | F10: Rutas
A11: 7 | B11: App del conductor en español y simple | C11: Se entiende sin capacitación larga y funciona en teléfonos comunes y con internet limitado. | D11: 7 | E11: Sí | F11: Ambos
A12: 8 | B12: Prueba de entrega y estado de paradas | C12: Foto o firma y estado de cada parada (entregada, fallida, motivo). | D12: 4 | E12: No | F12: Rutas
A13: 9 | B13: Hora estimada y aviso al cliente | C13: Calcula la hora estimada de llegada y avisa al cliente solo. | D13: 3 | E13: No | F13: Rutas
A14: 10 | B14: Exportar datos | C14: Se pueden sacar los datos en CSV, Google Sheets o conexión (API) para tus tableros. 1 = no se puede; 5 = automático. | D14: 7 | E14: Sí | F14: Ambos
A15: 11 | B15: Facilidad de uso para el supervisor | C15: Un supervisor nuevo lo domina en pocos días y encuentra rápido lo que necesita. | D15: 7 | E15: No | F15: Ambos
A16: 12 | B16: Costo total | C16: Se puntúa con la hoja Costos: equipo, instalación y mensualidad durante 24 meses. 1 = muy caro para el valor; 5 = muy competitivo. | D16: 12 | E16: No | F16: Ambos
... A19: 15 | B19: Privacidad y seguridad de datos | C19: Acceso por roles, dónde se guardan los datos, registro de quién ve qué, y cumplimiento de las normas aplicables. | D19: 5 | E19: No | F19: Ambos
B20: Suma de pesos | C20: =IF(D20=100,"Correcto: suma 100","Revisa: los pesos deben sumar 100") -> Correcto: suma 100 | D20: =SUM(D5:D19) -> 100
B22: Si evalúas solo GPS, pon peso 0 a los criterios que aplican a Rutas (y al revés), y reparte el peso entre los demás hasta sumar 100.

Sheet Evaluación
A1: Evaluación de proveedores
A2: Califica de 1 a 5 justo después de cada demostración, con evidencia. Deja en blanco lo que no hayas visto. Escribe el nombre de cada proveedor en el encabezado (celdas azules).
A4: Criterio | B4: Peso (%) | C4: Elimin. | D4: Ejemplo (ficticio) | E4: Proveedor A | F4: Proveedor B | G4: Proveedor C | H4: Proveedor D | I4: Proveedor E
A5: =Criterios!B5 -> Seguimiento en vivo | B5: =Criterios!D5 -> 9 | C5: =Criterios!E5 -> No | D5: 4
A6: =Criterios!B6 -> Geocercas y alertas configurables | B6: =Criterios!D6 -> 7 | C6: =Criterios!E6 -> No | D6: 3
A7: =Criterios!B7 -> Historial y reportes | B7: =Criterios!D7 -> 7 | C7: =Criterios!E7 -> No | D7: 4
A8: =Criterios!B8 -> Cobertura y fiabilidad en nuestras zonas | B8: =Criterios!D8 -> 7 | C8: =Criterios!E8 -> Sí | D8: 3
A9: =Criterios!B9 -> Funciona con motos | B9: =Criterios!D9 -> 5 | C9: =Criterios!E9 -> No | D9: 5
A10: =Criterios!B10 -> Planificación de rutas con ventanas de tiempo | B10: =Criterios!D10 -> 7 | C10: =Criterios!E10 -> No | D10: 4
A11: =Criterios!B11 -> App del conductor en español y simple | B11: =Criterios!D11 -> 7 | C11: =Criterios!E11 -> Sí | D11: 5
A12: =Criterios!B12 -> Prueba de entrega y estado de paradas | B12: =Criterios!D12 -> 4 | C12: =Criterios!E12 -> No | D12: 3
A13: =Criterios!B13 -> Hora estimada y aviso al cliente | B13: =Criterios!D13 -> 3 | C13: =Criterios!E13 -> No | D13: 3
A14: =Criterios!B14 -> Exportar datos | B14: =Criterios!D14 -> 7 | C14: =Criterios!E14 -> Sí | D14: 4
A15: =Criterios!B15 -> Facilidad de uso para el supervisor | B15: =Criterios!D15 -> 7 | C15: =Criterios!E15 -> No | D15: 4
A16: =Criterios!B16 -> Costo total | B16: =Criterios!D16 -> 12 | C16: =Criterios!E16 -> No | D16: 3
... A19: =Criterios!B19 -> Privacidad y seguridad de datos | B19: =Criterios!D19 -> 5 | C19: =Criterios!E19 -> No | D19: 4
A21: Puntaje (0 a 100) | D21: =IF(SUMPRODUCT($B$5:$B$19*(D5:D19<>""))=0,"",SUMPRODUCT($B$5:$B$19*(D5:D19<>"")*D5:D19)/(5*SUMPRODUCT($B$5:$B$19*(D5:D19<>"")))*100) -> 74.8 | E21: =IF(SUMPRODUCT($B$5:$B$19*(E5:E19<>""))=0,"",SUMPRODUCT($B$5:$B$19*(E5:E19<>"")*E5:E19)/(5*SUMPRODUCT($B$5:$B$19*(E5:E19<>"")))*100) | F21: =IF(SUMPRODUCT($B$5:$B$19*(F5:F19<>""))=0,"",SUMPRODUCT($B$5:$B$19*(F5:F19<>"")*F5:F19)/(5*SUMPRODUCT($B$5:$B$19*(F5:F19<>"")))*100) | G21: =IF(SUMPRODUCT($B$5:$B$19*(G5:G19<>""))=0,"",SUMPRODUCT($B$5:$B$19*(G5:G19<>"")*G5:G19)/(5*SUMPRODUCT($B$5:$B$19*(G5:G19<>"")))*100) | H21: =IF(SUMPRODUCT($B$5:$B$19*(H5:H19<>""))=0,"",SUMPRODUCT($B$5:$B$19*(H5:H19<>"")*H5:H19)/(5*SUMPRODUCT($B$5:$B$19*(H5:H19<>"")))*100) | I21: =IF(SUMPRODUCT($B$5:$B$19*(I5:I19<>""))=0,"",SUMPRODUCT($B$5:$B$19*(I5:I19<>"")*I5:I19)/(5*SUMPRODUCT($B$5:$B$19*(I5:I19<>"")))*100)
A22: Posición | D22: - | E22: =IF(E24="Evaluado",1+COUNTIFS($E$24:$I$24,"Evaluado",$E$21:$I$21,">"&E21),"-") -> - | F22: =IF(F24="Evaluado",1+COUNTIFS($E$24:$I$24,"Evaluado",$E$21:$I$21,">"&F21),"-") -> - | G22: =IF(G24="Evaluado",1+COUNTIFS($E$24:$I$24,"Evaluado",$E$21:$I$21,">"&G21),"-") -> - | H22: =IF(H24="Evaluado",1+COUNTIFS($E$24:$I$24,"Evaluado",$E$21:$I$21,">"&H21),"-") -> - | I22: =IF(I24="Evaluado",1+COUNTIFS($E$24:$I$24,"Evaluado",$E$21:$I$21,">"&I21),"-") -> -
A23: Criterios sin calificar | D23: =COUNTBLANK(D5:D19) -> 0 | E23: =COUNTBLANK(E5:E19) -> 15 | F23: =COUNTBLANK(F5:F19) -> 15 | G23: =COUNTBLANK(G5:G19) -> 15 | H23: =COUNTBLANK(H5:H19) -> 15 | I23: =COUNTBLANK(I5:I19) -> 15
A24: Estado | D24: =IF(D23=15,"Sin datos",IF(SUMPRODUCT(($C$5:$C$19="Sí")*(D5:D19<>"")*(D5:D19<=2))>0,"Descartado",IF(D23>0,"Incompleto","Evaluado"))) -> Evaluado | E24: =IF(E23=15,"Sin datos",IF(SUMPRODUCT(($C$5:$C$19="Sí")*(E5:E19<>"")*(E5:E19<=2))>0,"Descartado",IF(E23>0,"Incompleto","Evaluado"))) -> Sin datos | F24: =IF(F23=15,"Sin datos",IF(SUMPRODUCT(($C$5:$C$19="Sí")*(F5:F19<>"")*(F5:F19<=2))>0,"Descartado",IF(F23>0,"Incompleto","Evaluado"))) -> Sin datos | G24: =IF(G23=15,"Sin datos",IF(SUMPRODUCT(($C$5:$C$19="Sí")*(G5:G19<>"")*(G5:G19<=2))>0,"Descartado",IF(G23>0,"Incompleto","Evaluado"))) -> Sin datos | H24: =IF(H23=15,"Sin datos",IF(SUMPRODUCT(($C$5:$C$19="Sí")*(H5:H19<>"")*(H5:H19<=2))>0,"Descartado",IF(H23>0,"Incompleto","Evaluado"))) -> Sin datos | I24: =IF(I23=15,"Sin datos",IF(SUMPRODUCT(($C$5:$C$19="Sí")*(I5:I19<>"")*(I5:I19<=2))>0,"Descartado",IF(I23>0,"Incompleto","Evaluado"))) -> Sin datos
A25: Suma de pesos | B25: =SUM(B5:B19) -> 100 | C25: =IF(B25=100,"","Los pesos no suman 100: corrige en Criterios")
A27: Cómo leer el resultado
A28: El puntaje es el promedio ponderado de lo calificado, convertido a 0 a 100. Los criterios sin calificar no cuentan ni suman ni restan.
A29: Descartado: sacó 2 o menos en un criterio eliminatorio. Aunque tenga buen puntaje, no pasa.
A30: Incompleto: faltan criterios por calificar; no compares su puntaje con el de otro proveedor hasta completar.
A31: La posición solo se calcula para proveedores en estado Evaluado (todo calificado y sin descartar). Así un proveedor a medio calificar no aparece primero.
A32: No uses el puntaje como única razón: úsalo para decidir quién pasa a la prueba piloto.

Sheet Costos
A1: Costo total por proveedor
A2: Pide cada precio por escrito, con impuestos incluidos. Los valores de la columna de ejemplo son ficticios.
A4: Número de vehículos | B4: 24
A5: Moneda | B5: DOP
A7: Concepto | B7: Ejemplo (ficticio) | C7: =Evaluación!E4 -> Proveedor A | D7: =Evaluación!F4 -> Proveedor B | E7: =Evaluación!G4 -> Proveedor C | F7: =Evaluación!H4 -> Proveedor D | G7: =Evaluación!I4 -> Proveedor E
A8: Equipo por vehículo | B8: 3500
A9: Instalación por vehículo | B9: 800
A10: Mensualidad por vehículo | B10: 650
A11: Cargos fijos mensuales (plataforma, soporte) | B11: 2000
A12: Meses de contrato exigidos | B12: 12
A13: Costo inicial (equipo e instalación) | B13: =IF(COUNT(B8:B11)<4,"",$B$4*(B8+B9)) -> 103200 | C13: =IF(COUNT(C8:C11)<4,"",$B$4*(C8+C9)) | D13: =IF(COUNT(D8:D11)<4,"",$B$4*(D8+D9)) | E13: =IF(COUNT(E8:E11)<4,"",$B$4*(E8+E9)) | F13: =IF(COUNT(F8:F11)<4,"",$B$4*(F8+F9)) | G13: =IF(COUNT(G8:G11)<4,"",$B$4*(G8+G9))
A14: Costo mensual | B14: =IF(COUNT(B8:B11)<4,"",$B$4*B10+B11) -> 17600 | C14: =IF(COUNT(C8:C11)<4,"",$B$4*C10+C11) | D14: =IF(COUNT(D8:D11)<4,"",$B$4*D10+D11) | E14: =IF(COUNT(E8:E11)<4,"",$B$4*E10+E11) | F14: =IF(COUNT(F8:F11)<4,"",$B$4*F10+F11) | G14: =IF(COUNT(G8:G11)<4,"",$B$4*G10+G11)
A15: Total a 12 meses | B15: =IF(B13="","",B13+12*B14) -> 314400 | C15: =IF(C13="","",C13+12*C14) | D15: =IF(D13="","",D13+12*D14) | E15: =IF(E13="","",E13+12*E14) | F15: =IF(F13="","",F13+12*F14) | G15: =IF(G13="","",G13+12*G14)
A16: Total a 24 meses | B16: =IF(B13="","",B13+24*B14) -> 525600 | C16: =IF(C13="","",C13+24*C14) | D16: =IF(D13="","",D13+24*D14) | E16: =IF(E13="","",E13+24*E14) | F16: =IF(F13="","",F13+24*F14) | G16: =IF(G13="","",G13+24*G14)
A17: Costo por vehículo y por mes (24 meses) | B17: =IF(B16="","",B16/(24*$B$4)) -> 912.5 | C17: =IF(C16="","",C16/(24*$B$4)) | D17: =IF(D16="","",D16/(24*$B$4)) | E17: =IF(E16="","",E16/(24*$B$4)) | F17: =IF(F16="","",F16/(24*$B$4)) | G17: =IF(G16="","",G16/(24*$B$4))
A18: Compromiso mínimo del contrato | B18: =IF(OR(B12="",B14=""),"",B13+B12*B14) -> 314400 | C18: =IF(OR(C12="",C14=""),"",C13+C12*C14) | D18: =IF(OR(D12="",D14=""),"",D13+D12*D14) | E18: =IF(OR(E12="",E14=""),"",E13+E12*E14) | F18: =IF(OR(F12="",F14=""),"",F13+F12*F14) | G18: =IF(OR(G12="",G14=""),"",G13+G12*G14)
A20: Notas
A21: Fórmulas: costo inicial = vehículos por (equipo + instalación); costo mensual = vehículos por mensualidad + cargos fijos.
A22: Compara siempre el total a 24 meses, no solo la mensualidad: unos cobran más por el equipo y menos al mes, y al revés.
A23: Pregunta qué no está incluido (reposición de equipos dañados, cambios de vehículo, capacitación, soporte fuera de horario).
A24: Si el precio es en dólares, cambia la moneda arriba y usa un tipo de cambio fijo escrito en la cotización.
A25: Puntúa el criterio Costo total en la hoja Evaluación según estos totales y el valor que recibes.

Sheet Preguntas
A1: Preguntas para la demostración
A2: Haz las mismas preguntas a todos y anota la respuesta en la columna de cada proveedor. Pide que muestren, no que cuenten.
A4: Categoría | B4: Pregunta | C4: Por qué importa | D4: =Evaluación!E4 -> Proveedor A | E4: =Evaluación!F4 -> Proveedor B | F4: =Evaluación!G4 -> Proveedor C
A5: Equipo y cobertura | B5: ¿Cada cuántos segundos se actualiza la posición y qué pasa cuando no hay señal? | C5: Define qué tan en vivo es el seguimiento y qué pasa en zonas sin cobertura.
A6: Equipo y cobertura | B6: ¿Qué equipo se instala en las motos? ¿Funciona con el teléfono del conductor? ¿Cuánto dura la batería? | C6: Las motos son la mayor parte de la flota.
A7: Equipo y cobertura | B7: ¿Funciona en las rutas largas (Santiago, Punta Cana)? ¿Hay tramos sin cobertura? | C7: Las rutas largas son las más caras de perder de vista.
A8: Equipo y cobertura | B8: ¿Cuánto tarda la instalación por vehículo y dónde se hace? | C8: Un vehículo parado instalándose no entrega.
A9: Funciones | B9: ¿Se pueden crear geocercas y alertas (llegada, salida, desvío, parada larga, exceso de velocidad)? ¿A quién llegan y por qué medio? | C9: Es lo que te permite gestionar por excepción.
A10: Funciones | B10: ¿Qué reportes trae (ralentí, frenazos, kilómetros, combustible)? ¿Se pueden programar por correo? | C10: Es la base del entrenamiento de conductores y del ahorro de combustible.
A11: Funciones | B11: ¿Se puede comparar la ruta planificada con la ruta real? | C11: Mide si los conductores siguen el plan.
A12: Funciones | B12: Si es software de rutas: ¿acepta ventanas de tiempo, varios tipos de vehículo y reasignar paradas durante el día? | C12: Define si sirve para tu operación real.
A13: Funciones | B13: ¿Hay prueba de entrega (foto, firma) y aviso automático al cliente? | C13: Reduce llamadas y disputas.
A14: Uso | B14: ¿La app del conductor está en español? ¿Funciona en teléfonos básicos y con poco internet? | C14: Si los conductores no la usan, no hay datos.
A15: Uso | B15: ¿Cuánto tarda un supervisor nuevo en aprender? ¿La capacitación está incluida? | C15: El costo real incluye el tiempo del equipo.
A16: Datos | B16: ¿Se pueden exportar los datos (CSV, Google Sheets, API)? ¿Con qué frecuencia? | C16: Sin exportar no puedes conectar tus tableros.
... A23: Prueba | B23: ¿Pueden darnos una prueba de 2 semanas con 3 a 5 vehículos y referencias de clientes con una flota parecida? | C23: La demostración muestra lo mejor; el piloto muestra la realidad.

Sheet Piloto
A1: Prueba piloto
A2: Una demostración muestra lo mejor del producto. El piloto muestra cómo funciona en tu operación. Decide qué resultado esperas ANTES de empezar.
A4: Proveedor probado | C4: Ejemplo: Proveedor A
A5: Vehículos del piloto (mezcla de tipos) | C5: Ejemplo: V01 (moto), V15 (furgoneta), V21 (camión)
A6: Fecha de inicio
A7: Fecha de fin (unas 2 semanas)
A8: Resultado mínimo para elegirlo | C8: Ejemplo: reducir las llamadas a conductores a la mitad, sin fallas graves del equipo
A10: Medida | B10: Mejor si | C10: Antes (línea base) | D10: Durante el piloto | E10: Cambio % | F10: Resultado | G10: Cómo medirlo
A11: Ejemplo: llamadas a conductores por día | B11: Baja | C11: 40 | D11: 22 | E11: =IF(OR(C11="",D11="",C11=0),"",(D11-C11)/C11) -> -0.45 | F11: =IF(OR(C11="",D11=""),"",IF(D11=C11,"Igual",IF(OR(AND(B11="Baja",D11<C11),AND(B11="Sube",D11>C11)),"Mejoró","Empeoró"))) -> Mejoró | G11: Ejemplo ficticio: borra esta fila de ejemplo o ignórala.
A12: Llamadas a conductores por día | B12: Baja | E12: =IF(OR(C12="",D12="",C12=0),"",(D12-C12)/C12) | F12: =IF(OR(C12="",D12=""),"",IF(D12=C12,"Igual",IF(OR(AND(B12="Baja",D12<C12),AND(B12="Sube",D12>C12)),"Mejoró","Empeoró"))) | G12: Cuenta las llamadas y mensajes de seguimiento del supervisor durante una semana antes y una durante.
A13: Minutos para saber dónde está cada ruta (promedio) | B13: Baja | E13: =IF(OR(C13="",D13="",C13=0),"",(D13-C13)/C13) | F13: =IF(OR(C13="",D13=""),"",IF(D13=C13,"Igual",IF(OR(AND(B13="Baja",D13<C13),AND(B13="Sube",D13>C13)),"Mejoró","Empeoró"))) | G13: Cronometra 5 veces al día cuánto tarda el supervisor en tener la posición de todas las rutas.
A14: Rutas atrasadas por semana | B14: Baja | E14: =IF(OR(C14="",D14="",C14=0),"",(D14-C14)/C14) | F14: =IF(OR(C14="",D14=""),"",IF(D14=C14,"Igual",IF(OR(AND(B14="Baja",D14<C14),AND(B14="Sube",D14>C14)),"Mejoró","Empeoró"))) | G14: Cuenta en la pestaña Hoy las rutas con estado Atrasada.
A15: Incidencias sin código de motivo por semana | B15: Baja | E15: =IF(OR(C15="",D15="",C15=0),"",(D15-C15)/C15) | F15: =IF(OR(C15="",D15=""),"",IF(D15=C15,"Igual",IF(OR(AND(B15="Baja",D15<C15),AND(B15="Sube",D15>C15)),"Mejoró","Empeoró"))) | G15: Cuenta las que aparecen marcadas en verificacion_datos.
A16: Minutos en armar el plan del día | B16: Baja | E16: =IF(OR(C16="",D16="",C16=0),"",(D16-C16)/C16) | F16: =IF(OR(C16="",D16=""),"",IF(D16=C16,"Igual",IF(OR(AND(B16="Baja",D16<C16),AND(B16="Sube",D16>C16)),"Mejoró","Empeoró"))) | G16: Mide cuánto tarda el supervisor en asignar y revisar las rutas cada mañana.
A17: Desvío de km real frente al plan (%) | B17: Baja | E17: =IF(OR(C17="",D17="",C17=0),"",(D17-C17)/C17) | F17: =IF(OR(C17="",D17=""),"",IF(D17=C17,"Igual",IF(OR(AND(B17="Baja",D17<C17),AND(B17="Sube",D17>C17)),"Mejoró","Empeoró"))) | G17: Compara km reales con km planificados de las rutas del piloto.
A18: Fallas técnicas del equipo o la app (cantidad) | B18: Baja | E18: =IF(OR(C18="",D18="",C18=0),"",(D18-C18)/C18) | F18: =IF(OR(C18="",D18=""),"",IF(D18=C18,"Igual",IF(OR(AND(B18="Baja",D18<C18),AND(B18="Sube",D18>C18)),"Mejoró","Empeoró"))) | G18: Anota cada falla: equipo sin señal, app que no abre, datos que no llegan.
A19: Satisfacción del supervisor (1 a 5) | B19: Sube | E19: =IF(OR(C19="",D19="",C19=0),"",(D19-C19)/C19) | F19: =IF(OR(C19="",D19=""),"",IF(D19=C19,"Igual",IF(OR(AND(B19="Baja",D19<C19),AND(B19="Sube",D19>C19)),"Mejoró","Empeoró"))) | G19: Una pregunta al terminar el piloto.
A20: Satisfacción de los conductores (1 a 5) | B20: Sube | E20: =IF(OR(C20="",D20="",C20=0),"",(D20-C20)/C20) | F20: =IF(OR(C20="",D20=""),"",IF(D20=C20,"Igual",IF(OR(AND(B20="Baja",D20<C20),AND(B20="Sube",D20>C20)),"Mejoró","Empeoró"))) | G20: Promedio de una pregunta a cada conductor del piloto.
A22: Medidas que mejoraron | B22: =COUNTIF(F12:F20,"Mejoró") -> 0
A23: Medidas que empeoraron | B23: =COUNTIF(F12:F20,"Empeoró") -> 0
A25: Decisión
A26: Motivo de la decisión
A28: Los conteos de arriba ignoran la fila de ejemplo.
